yatom/__init__.py
yatom/loader.py
yatom/processor/__init__.py
yatom/processor/base.py
yatom/processor/html.py
yatom/processor/xml.py
yatom/tests/__init__.py
yatom/tests/html.py
yatom/tests/meta.py
yatom/tests/resources/__init__.py
yatom/tests/resources/__init__.pyc
yatom/tests/resources/attributes.html
yatom/tests/resources/attributes.yml
yatom/tests/resources/form.html
yatom/tests/resources/form.yml
yatom/tests/resources/page.html
yatom/tests/resources/page.yml
yatom/tests/resources/xhtml.html
yatom/tests/resources/xhtml.yml
yatom-0.0.4.dist-info/LICENSE
yatom-0.0.4.dist-info/METADATA
yatom-0.0.4.dist-info/WHEEL
yatom-0.0.4.dist-info/top_level.txt
yatom-0.0.4.dist-info/zip-safe
yatom-0.0.4.dist-info/RECORD
