Metadata-Version: 2.1
Name: yatom
Version: 0.0.4
Summary: Beautiful HTML/XHTML/XML using YAML
Home-page: https://gitlab.com/ergoithz/yatom
Author: Felipe A. Hernandez
Author-email: ergoithz@gmail.com
License: MIT
Keywords: yaml,html
Platform: any
Classifier: Development Status :: 4 - Beta
Classifier: License :: OSI Approved :: MIT License
Classifier: Operating System :: OS Independent
Classifier: Programming Language :: Python :: 3
Classifier: Topic :: Text Processing :: Markup
Classifier: Topic :: Text Processing :: Markup :: HTML
Classifier: Topic :: Text Processing :: Markup :: XML
Requires-Dist: pyyaml
Requires-Dist: six
